Metadata-Version: 2.1
Name: user-friendly-id
Version: 1.0.0
Summary: Collection of functions to randomly and securely generate commonly used IDs.
Home-page: https://github.com/lapinvert/user-friendly-id/
Author: Remy Charlot <remy@personalstock.com>
Author-email: remy@personalstock.com
License: BSD
Keywords: generator,strings,string,str,generate,user,user-friendly,ID,IDs,secure,safe
Platform: UNKNOWN
Classifier: Programming Language :: Python
Classifier: Topic :: Software Development :: Libraries :: Python Modules
Classifier: License :: OSI Approved :: BSD License
Classifier: Environment :: Web Environment
Classifier: Development Status :: 5 - Production/Stable
Classifier: Programming Language :: Python :: 3.4
Classifier: Programming Language :: Python :: 3.5
Classifier: Programming Language :: Python :: 3.6
Classifier: Programming Language :: Python :: 3.8
